{"kd_tree_not_leaf_node": [{"hrect": [[30.410548, 103.455747], [30.8383, 104.276514]], "left_nodeptr": 32, "right_nodeptr": 1}, {"hrect": [[30.651933, 103.455747], [30.8383, 104.276514]], "left_nodeptr": 17, "right_nodeptr": 2}, {"hrect": [[30.651933, 104.066343], [30.8383, 104.276514]], "left_nodeptr": 10, "right_nodeptr": 3}, {"hrect": [[30.671479, 104.066343], [30.8383, 104.276514]], "left_nodeptr": 7, "right_nodeptr": 4}, {"hrect": [[30.671479, 104.088029], [30.8383, 104.276514]], "left_nodeptr": 6, "right_nodeptr": 5}, {"hrect": [[30.68986, 104.088029], [30.8383, 104.276514]], "left_nodeptr": -1, "right_nodeptr": -1}, {"hrect": [[30.671479, 104.088029], [30.68986, 104.276514]], "left_nodeptr": -1, "right_nodeptr": -1}, {"hrect": [[30.671479, 104.066343], [30.8383, 104.088029]], "left_nodeptr": 9, "right_nodeptr": 8}, {"hrect": [[30.682824, 104.066343], [30.8383, 104.088029]], "left_nodeptr": -1, "right_nodeptr": -1}, {"hrect": [[30.671479, 104.066343], [30.682824, 104.088029]], "left_nodeptr": -1, "right_nodeptr": -1}, {"hrect": [[30.651933, 104.066343], [30.671479, 104.276514]], "left_nodeptr": 14, "right_nodeptr": 11}, {"hrect": [[30.651933, 104.080883], [30.671479, 104.276514]], "left_nodeptr": 13, "right_nodeptr": 12}, {"hrect": [[30.661782, 104.080883], [30.671479, 104.276514]], "left_nodeptr": -1, "right_nodeptr": -1}, {"hrect": [[30.651933, 104.080883], [30.661782, 104.276514]], "left_nodeptr": -1, "right_nodeptr": -1}, {"hrect": [[30.651933, 104.066343], [30.671479, 104.080883]], "left_nodeptr": 16, "right_nodeptr": 15}, {"hrect": [[30.658752, 104.066343], [30.671479, 104.080883]], "left_nodeptr": -1, "right_nodeptr": -1}, {"hrect": [[30.651933, 104.066343], [30.658752, 104.080883]], "left_nodeptr": -1, "right_nodeptr": -1}, {"hrect": [[30.651933, 103.455747], [30.8383, 104.066343]], "left_nodeptr": 25, "right_nodeptr": 18}, {"hrect": [[30.674845, 103.455747], [30.8383, 104.066343]], "left_nodeptr": 22, "right_nodeptr": 19}, {"hrect": [[30.674845, 104.032051], [30.8383, 104.066343]], "left_nodeptr": 21, "right_nodeptr": 20}, {"hrect": [[30.69096, 104.032051], [30.8383, 104.066343]], "left_nodeptr": -1, "right_nodeptr": -1}, {"hrect": [[30.674845, 104.032051], [30.69096, 104.066343]], "left_nodeptr": -1, "right_nodeptr": -1}, {"hrect": [[30.674845, 103.455747], [30.8383, 104.032051]], "left_nodeptr": 24, "right_nodeptr": 23}, {"hrect": [[30.696644, 103.455747], [30.8383, 104.032051]], "left_nodeptr": -1, "right_nodeptr": -1}, {"hrect": [[30.674845, 103.455747], [30.696644, 104.032051]], "left_nodeptr": -1, "right_nodeptr": -1}, {"hrect": [[30.651933, 103.455747], [30.674845, 104.066343]], "left_nodeptr": 29, "right_nodeptr": 26}, {"hrect": [[30.651933, 104.0462], [30.674845, 104.066343]], "left_nodeptr": 28, "right_nodeptr": 27}, {"hrect": [[30.665365, 104.0462], [30.674845, 104.066343]], "left_nodeptr": -1, "right_nodeptr": -1}, {"hrect": [[30.651933, 104.0462], [30.665365, 104.066343]], "left_nodeptr": -1, "right_nodeptr": -1}, {"hrect": [[30.651933, 103.455747], [30.674845, 104.0462]], "left_nodeptr": 31, "right_nodeptr": 30}, {"hrect": [[30.665295, 103.455747], [30.674845, 104.0462]], "left_nodeptr": -1, "right_nodeptr": -1}, {"hrect": [[30.651933, 103.455747], [30.665295, 104.0462]], "left_nodeptr": -1, "right_nodeptr": -1}, {"hrect": [[30.410548, 103.455747], [30.651933, 104.276514]], "left_nodeptr": 48, "right_nodeptr": 33}, {"hrect": [[30.410548, 104.066547], [30.651933, 104.276514]], "left_nodeptr": 41, "right_nodeptr": 34}, {"hrect": [[30.627919, 104.066547], [30.651933, 104.276514]], "left_nodeptr": 38, "right_nodeptr": 35}, {"hrect": [[30.627919, 104.09099], [30.651933, 104.276514]], "left_nodeptr": 37, "right_nodeptr": 36}, {"hrect": [[30.639194, 104.09099], [30.651933, 104.276514]], "left_nodeptr": -1, "right_nodeptr": -1}, {"hrect": [[30.627919, 104.09099], [30.639194, 104.276514]], "left_nodeptr": -1, "right_nodeptr": -1}, {"hrect": [[30.627919, 104.066547], [30.651933, 104.09099]], "left_nodeptr": 40, "right_nodeptr": 39}, {"hrect": [[30.644103, 104.066547], [30.651933, 104.09099]], "left_nodeptr": -1, "right_nodeptr": -1}, {"hrect": [[30.627919, 104.066547], [30.644103, 104.09099]], "left_nodeptr": -1, "right_nodeptr": -1}, {"hrect": [[30.410548, 104.066547], [30.627919, 104.276514]], "left_nodeptr": 45, "right_nodeptr": 42}, {"hrect": [[30.410548, 104.079936], [30.627919, 104.276514]], "left_nodeptr": 44, "right_nodeptr": 43}, {"hrect": [[30.614573, 104.079936], [30.627919, 104.276514]], "left_nodeptr": -1, "right_nodeptr": -1}, {"hrect": [[30.410548, 104.079936], [30.614573, 104.276514]], "left_nodeptr": -1, "right_nodeptr": -1}, {"hrect": [[30.410548, 104.066547], [30.627919, 104.079936]], "left_nodeptr": 47, "right_nodeptr": 46}, {"hrect": [[30.610853, 104.066547], [30.627919, 104.079936]], "left_nodeptr": -1, "right_nodeptr": -1}, {"hrect": [[30.410548, 104.066547], [30.610853, 104.079936]], "left_nodeptr": -1, "right_nodeptr": -1}, {"hrect": [[30.410548, 103.455747], [30.651933, 104.066547]], "left_nodeptr": 56, "right_nodeptr": 49}, {"hrect": [[30.629231, 103.455747], [30.651933, 104.066547]], "left_nodeptr": 53, "right_nodeptr": 50}, {"hrect": [[30.629231, 104.041372], [30.651933, 104.066547]], "left_nodeptr": 52, "right_nodeptr": 51}, {"hrect": [[30.642327, 104.041372], [30.651933, 104.066547]], "left_nodeptr": -1, "right_nodeptr": -1}, {"hrect": [[30.629231, 104.041372], [30.642327, 104.066547]], "left_nodeptr": -1, "right_nodeptr": -1}, {"hrect": [[30.629231, 103.455747], [30.651933, 104.041372]], "left_nodeptr": 55, "right_nodeptr": 54}, {"hrect": [[30.640555, 103.455747], [30.651933, 104.041372]], "left_nodeptr": -1, "right_nodeptr": -1}, {"hrect": [[30.629231, 103.455747], [30.640555, 104.041372]], "left_nodeptr": -1, "right_nodeptr": -1}, {"hrect": [[30.410548, 103.455747], [30.629231, 104.066547]], "left_nodeptr": 60, "right_nodeptr": 57}, {"hrect": [[30.410548, 104.048447], [30.629231, 104.066547]], "left_nodeptr": 59, "right_nodeptr": 58}, {"hrect": [[30.600331, 104.048447], [30.629231, 104.066547]], "left_nodeptr": -1, "right_nodeptr": -1}, {"hrect": [[30.410548, 104.048447], [30.600331, 104.066547]], "left_nodeptr": -1, "right_nodeptr": -1}, {"hrect": [[30.410548, 103.455747], [30.629231, 104.048447]], "left_nodeptr": 62, "right_nodeptr": 61}, {"hrect": [[30.603707, 103.455747], [30.629231, 104.048447]], "left_nodeptr": -1, "right_nodeptr": -1}, {"hrect": [[30.410548, 103.455747], [30.603707, 104.048447]], "left_nodeptr": -1, "right_nodeptr": -1}], "idx_gps": [[30.705708, 104.103833], [30.680456, 104.125379], [30.695484, 104.072634], [30.677128, 104.077581], [30.666396, 104.109999], [30.657234, 104.112297], [30.664451, 104.077588], [30.65511, 104.070718], [30.706495, 104.053071], [30.683285, 104.043731], [30.708014, 104.019944], [30.683238, 104.026477], [30.6701, 104.063605], [30.659324, 104.05601], [30.66947, 104.040704], [30.662308, 104.025741], [30.646298, 104.104066], [30.634117, 104.151206], [30.647863, 104.088093], [30.639069, 104.089248], [30.623117, 104.100638], [30.602037, 104.100624], [30.618783, 104.067288], [30.590332, 104.07109], [30.645074, 104.062716], [30.636871, 104.053712], [30.646741, 103.985829], [30.634443, 104.008722], [30.616072, 104.065263], [30.588431, 104.054601], [30.62097, 104.039782], [30.573472, 103.958173]], "sum_matrix": [[166, 62, 80, 27, 44, 22, 24, 15, 26, 12, 14, 10, 10, 11, 5, 2, 20, 23, 11, 11, 10, 12, 2, 0, 4, 7, 3, 4, 2, 1, 1, 4], [65, 111, 46, 69, 77, 61, 43, 27, 14, 16, 6, 7, 18, 13, 7, 6, 25, 22, 25, 15, 14, 5, 12, 6, 9, 8, 2, 1, 6, 0, 4, 9], [77, 46, 97, 32, 20, 11, 22, 14, 47, 24, 29, 18, 26, 16, 15, 14, 5, 18, 12, 4, 9, 3, 2, 1, 13, 10, 2, 1, 2, 1, 8, 4], [35, 39, 59, 131, 19, 20, 43, 23, 16, 31, 11, 8, 38, 28, 10, 10, 7, 12, 20, 14, 8, 4, 12, 5, 20, 9, 3, 3, 3, 2, 4, 6], [35, 80, 43, 46, 98, 70, 40, 49, 10, 14, 6, 9, 11, 17, 4, 8, 38, 25, 38, 20, 14, 14, 8, 9, 22, 12, 5, 1, 2, 1, 6, 4], [31, 43, 23, 37, 57, 76, 45, 54, 5, 7, 7, 1, 18, 26, 3, 7, 56, 39, 61, 21, 17, 9, 18, 3, 31, 14, 4, 5, 4, 4, 4, 11], [23, 17, 29, 26, 28, 22, 56, 57, 15, 20, 9, 5, 34, 56, 16, 18, 15, 8, 35, 12, 8, 3, 4, 4, 32, 16, 4, 3, 9, 4, 7, 6], [21, 7, 11, 11, 13, 23, 37, 44, 5, 3, 2, 4, 18, 52, 4, 16, 10, 18, 59, 19, 6, 7, 7, 5, 51, 15, 5, 6, 5, 3, 3, 16], [28, 10, 78, 21, 9, 8, 10, 17, 147, 46, 76, 59, 30, 18, 21, 33, 0, 2, 9, 7, 4, 0, 3, 3, 18, 8, 11, 5, 3, 0, 7, 7], [25, 14, 51, 55, 10, 11, 25, 29, 62, 71, 36, 38, 70, 53, 37, 37, 6, 5, 12, 7, 2, 2, 9, 3, 35, 14, 13, 9, 4, 2, 4, 15], [16, 4, 27, 17, 1, 0, 4, 6, 88, 38, 227, 106, 14, 7, 29, 26, 0, 2, 1, 2, 3, 0, 2, 0, 10, 6, 17, 16, 0, 2, 9, 9], [10, 11, 14, 14, 4, 4, 15, 7, 56, 35, 86, 134, 20, 10, 80, 38, 3, 5, 5, 3, 2, 4, 11, 4, 12, 5, 41, 16, 6, 6, 12, 10], [11, 9, 29, 40, 18, 13, 45, 39, 29, 52, 16, 24, 75, 69, 25, 45, 11, 11, 18, 8, 3, 7, 11, 5, 47, 22, 8, 8, 5, 5, 8, 8], [9, 5, 10, 17, 8, 12, 53, 37, 9, 30, 5, 8, 49, 53, 17, 42, 5, 11, 22, 17, 3, 3, 7, 6, 48, 25, 15, 11, 4, 4, 7, 8], [16, 2, 24, 15, 0, 4, 22, 16, 26, 51, 42, 86, 30, 31, 107, 81, 3, 6, 13, 4, 2, 2, 6, 1, 34, 9, 38, 26, 5, 4, 13, 10], [2, 4, 12, 12, 9, 2, 11, 18, 21, 21, 18, 42, 23, 40, 64, 85, 2, 5, 21, 8, 4, 1, 5, 4, 35, 20, 60, 36, 11, 4, 17, 9], [22, 25, 12, 11, 51, 71, 33, 48, 5, 7, 2, 2, 13, 14, 8, 7, 109, 96, 38, 48, 40, 31, 33, 9, 12, 8, 3, 7, 12, 6, 6, 12], [17, 15, 12, 11, 27, 29, 9, 24, 4, 7, 0, 0, 6, 17, 11, 5, 66, 118, 26, 27, 85, 47, 19, 12, 11, 6, 0, 6, 12, 13, 7, 14], [14, 17, 18, 13, 17, 43, 51, 56, 3, 13, 0, 1, 11, 25, 3, 13, 33, 19, 70, 36, 18, 10, 22, 8, 37, 26, 3, 7, 3, 9, 9, 10], [16, 16, 7, 15, 12, 18, 23, 47, 1, 7, 1, 4, 9, 30, 8, 8, 35, 23, 50, 84, 27, 20, 47, 22, 38, 38, 10, 8, 15, 14, 10, 10], [13, 16, 10, 11, 22, 21, 21, 23, 4, 6, 2, 3, 7, 15, 1, 2, 36, 73, 35, 54, 104, 92, 34, 27, 9, 7, 6, 6, 12, 24, 19, 21], [12, 13, 6, 6, 12, 15, 11, 9, 5, 3, 2, 4, 6, 6, 4, 5, 16, 39, 12, 47, 97, 132, 63, 63, 8, 18, 3, 13, 27, 47, 16, 20], [1, 4, 2, 9, 11, 11, 16, 24, 4, 8, 1, 1, 6, 15, 3, 12, 11, 19, 23, 56, 23, 44, 61, 50, 25, 29, 11, 14, 48, 41, 31, 30], [1, 5, 1, 7, 5, 7, 3, 8, 4, 3, 3, 5, 2, 7, 1, 2, 4, 19, 13, 18, 25, 48, 59, 161, 6, 18, 5, 15, 38, 134, 24, 46], [12, 2, 13, 12, 5, 4, 22, 43, 8, 19, 9, 5, 20, 45, 18, 29, 5, 12, 22, 21, 13, 8, 13, 8, 70, 45, 28, 15, 13, 5, 15, 11], [8, 9, 6, 9, 6, 8, 16, 33, 9, 8, 7, 4, 17, 31, 15, 18, 8, 11, 20, 28, 17, 19, 26, 15, 39, 115, 28, 33, 40, 28, 47, 15], [6, 0, 16, 9, 1, 3, 13, 16, 13, 16, 19, 35, 15, 26, 51, 78, 4, 8, 23, 4, 5, 9, 20, 8, 28, 35, 116, 90, 12, 16, 50, 28], [6, 2, 6, 5, 0, 6, 8, 18, 11, 13, 9, 22, 12, 29, 26, 34, 1, 12, 7, 13, 9, 8, 25, 13, 25, 31, 76, 121, 22, 26, 93, 44], [6, 8, 1, 5, 3, 7, 13, 13, 2, 1, 2, 8, 12, 10, 7, 14, 8, 15, 21, 33, 26, 21, 86, 59, 21, 41, 14, 29, 128, 101, 64, 33], [0, 0, 0, 0, 2, 3, 5, 4, 0, 0, 2, 1, 3, 4, 0, 5, 2, 3, 3, 14, 6, 31, 25, 100, 9, 9, 6, 9, 35, 197, 28, 42], [3, 5, 7, 6, 5, 4, 11, 18, 5, 6, 14, 12, 6, 14, 22, 27, 6, 8, 3, 11, 7, 10, 37, 20, 20, 23, 34, 75, 31, 39, 116, 61], [4, 6, 3, 4, 3, 6, 5, 15, 5, 2, 3, 7, 3, 7, 5, 4, 5, 6, 10, 17, 9, 10, 23, 25, 7, 14, 8, 24, 25, 65, 41, 226]]}